text_structura/__init__.py
text_structura/main.py
text_structura/prompts.py
text_structura-2025.12.21090343.dist-info/METADATA
text_structura-2025.12.21090343.dist-info/WHEEL
text_structura-2025.12.21090343.dist-info/top_level.txt
text_structura-2025.12.21090343.dist-info/RECORD
