Metadata-Version: 2.4
Name: text-structura
Version: 2025.12.21090343
Summary: A new package that takes user-provided text input and returns structured, validated output using pattern matching to ensure consistent formatting. It processes text extracted from various sources like
Author-email: text-structura <hi@eugene.plus>
License: MIT
Project-URL: Homepage, https://github.com/chigwell/text-structura
Requires-Python: >=3.9
Requires-Dist: langchain-llm7>=0.0.0
Requires-Dist: llmatch-messages>=0.0.0
Requires-Dist: langchain-core>=0.3.0
